deeploupe/__init__.py
deeploupe-0.0.0.dist-info/LICENSE
deeploupe-0.0.0.dist-info/METADATA
deeploupe-0.0.0.dist-info/WHEEL
deeploupe-0.0.0.dist-info/top_level.txt
deeploupe-0.0.0.dist-info/RECORD
