Metadata-Version: 2.1
Name: deeploupe
Version: 0.0.0
Summary: Coming soon
Author: Heinrich Tremblay
Author-email: heinrich.tremblay@outlook.com
Classifier: Programming Language :: Python :: 3
Classifier: License :: OSI Approved :: MIT License
Classifier: Operating System :: OS Independent
Requires-Python: >=3.6
License-File: LICENSE
